{
    "plan":
    [
      {
        "title": "수정 제목",
        "content": "수정 내용",
        "id": 13
      },
      {
        "title": "수정 제목",
        "content": "수정 내용",
        "id": 14
      }
    ],
    "todayplan":
      [
        {
          "title": "수정 제목",
          "content": "수정 내용",
          "id": 13
        },
        {
          "title": "수정 제목",
          "content": "수정 내용",
          "id": 14
        }
    ],
    "pastplan":
     [
      {
        "title": "수정 제목",
        "content": "수정 내용",
        "id": 13
      },
      {
        "title": "수정 제목",
        "content": "수정 내용",
        "planPassword": 1234,
        "id": 14
      }
    ]

  }